csv_analyzer/__init__.py
csv_analyzer/logic.py
csv_analyzer/models.py
csv_analyzer1-0.1.1.dist-info/METADATA
csv_analyzer1-0.1.1.dist-info/WHEEL
csv_analyzer1-0.1.1.dist-info/top_level.txt
csv_analyzer1-0.1.1.dist-info/RECORD
