Metadata-Version: 2.4
Name: csv-analyzer1
Version: 0.1.1
Summary: Valide et charge des données CSV en objets Python
Author: Theme 7
Requires-Dist: pydantic
